click_demultiplex/VERSION
click_demultiplex/__init__.py
click_demultiplex/__main__.py
click_demultiplex/cli.py
click_demultiplex/commands.py
click_demultiplex/exceptions.py
click_demultiplex/utils.py
click_demultiplex/validators.py
click_demultiplex/data/README.md
click_demultiplex-0.1.0.dist-info/DESCRIPTION.rst
click_demultiplex-0.1.0.dist-info/METADATA
click_demultiplex-0.1.0.dist-info/RECORD
click_demultiplex-0.1.0.dist-info/WHEEL
click_demultiplex-0.1.0.dist-info/entry_points.txt
click_demultiplex-0.1.0.dist-info/metadata.json
click_demultiplex-0.1.0.dist-info/top_level.txt
tests/__init__.py
tests/test_commands.py
tests/test_utils.py
tests/test_validators.py
tests/test_version.py
