Metadata-Version: 2.0
Name: click-demultiplex
Version: 0.1.0
Summary: Command Line Tool to Demultiplex a paired-end fastq file into several fastq files,
Home-page: https://github.com/leukgen/click_demultiplex
Author: Juan E. Arango
Author-email: UNKNOWN
License: BSD
Platform: UNKNOWN
Classifier: Intended Audience :: Developers
Classifier: Intended Audience :: Science/Research
Classifier: License :: OSI Approved :: MIT License
Classifier: Natural Language :: English
Classifier: Operating System :: Unix
Classifier: Operating System :: POSIX
Classifier: Programming Language :: Python :: 2 :: Only
Classifier: Topic :: Utilities
Requires-Dist: Click (>=6.7)
Requires-Dist: biopython (==1.70)
Requires-Dist: pandas (==0.22.0)
Provides-Extra: test
Requires-Dist: coverage (>=4.4.2); extra == 'test'
Requires-Dist: pydocstyle (>=2.1.1); extra == 'test'
Requires-Dist: pytest-cov (>=2.5.1); extra == 'test'
Requires-Dist: pytest-env (==0.6.2); extra == 'test'
Requires-Dist: pylint (>=1.8.1); extra == 'test'
Requires-Dist: tox (==2.9.1); extra == 'test'
